{"records": [{"adm0_name": "Madagascar", "adm0_code": 150, "population": 5745239, "loss": 593416.6751035281, "wind_cat": {"0": 4181376, "1": 1563863}, "adm1": [{"adm1_name": "Alaotra Mangoro", "adm1_code": 41750, "population": 3375, "loss": 0.2616177632, "wind_cat": {"0": 3375}, "adm2": [{"adm2_name": "Anosibe An'Ala", "adm2_code": 19260, "population": 3375, "loss": 0.2616177632, "wind_cat": {"0": 3375}}]}, {"adm1_name": "Amoron'i Mania", "adm1_code": 41751, "population": 639824, "loss": 208612.3290781797, "wind_cat": {"0": 221790, "1": 418034}, "adm2": [{"adm2_name": "Ambatofinandrahana", "adm2_code": 19214, "population": 202188, "loss": 87196.2266491717, "wind_cat": {"0": 50065, "1": 152123}}, {"adm2_name": "Ambositra", "adm2_code": 19216, "population": 237506, "loss": 72889.6250061714, "wind_cat": {"0": 73715, "1": 163791}}, {"adm2_name": "Fandriana", "adm2_code": 19218, "population": 130358, "loss": 11725.7673565065, "wind_cat": {"0": 71764, "1": 58594}}, {"adm2_name": "Manandriana", "adm2_code": 19229, "population": 69772, "loss": 36800.7100663301, "wind_cat": {"0": 26246, "1": 43526}}]}, {"adm1_name": "Analamanga", "adm1_code": 41752, "population": 36802, "loss": 0.4933984498, "wind_cat": {"0": 36802}, "adm2": [{"adm2_name": "Andramasina", "adm2_code": 19187, "population": 36802, "loss": 0.4933984498, "wind_cat": {"0": 36802}}]}, {"adm1_name": "Anosy", "adm1_code": 41755, "population": 8220, "loss": 0.9941430099, "wind_cat": {"0": 8220}, "adm2": [{"adm2_name": "Betroka", "adm2_code": 19285, "population": 8220, "loss": 0.9941430099, "wind_cat": {"0": 8220}}]}, {"adm1_name": "Atsimo Andrefana", "adm1_code": 41756, "population": 173608, "loss": 10049.7603096207, "wind_cat": {"0": 167463, "1": 6145}, "adm2": [{"adm2_name": "Ankazoabo", "adm2_code": 19278, "population": 54344, "loss": 1279.476186915, "wind_cat": {"0": 52514, "1": 1830}}, {"adm2_name": "Beroroha", "adm2_code": 19283, "population": 30295, "loss": 8665.465639578, "wind_cat": {"0": 25980, "1": 4315}}, {"adm2_name": "Morombe", "adm2_code": 19289, "population": 57364, "loss": 87.7955561258, "wind_cat": {"0": 57364}}, {"adm2_name": "Sakaraha", "adm2_code": 19291, "population": 31605, "loss": 17.0229270019, "wind_cat": {"0": 31605}}]}, {"adm1_name": "Atsimo Atsinanana", "adm1_code": 41757, "population": 10568, "loss": 0.069234722, "wind_cat": {"0": 10568}, "adm2": [{"adm2_name": "Farafangana", "adm2_code": 19219, "population": 4870, "loss": 0.0430346033, "wind_cat": {"0": 4870}}, {"adm2_name": "Vondrozo", "adm2_code": 19235, "population": 5698, "loss": 0.0262001187, "wind_cat": {"0": 5698}}]}, {"adm1_name": "Atsinanana", "adm1_code": 41758, "population": 41151, "loss": 160.7584688609, "wind_cat": {"0": 41151}, "adm2": [{"adm2_name": "Mahanoro", "adm2_code": 19263, "population": 6829, "loss": 0.2187132742, "wind_cat": {"0": 6829}}, {"adm2_name": "Marolambo", "adm2_code": 19266, "population": 34322, "loss": 160.5397555868, "wind_cat": {"0": 34322}}]}, {"adm1_name": "Bongolava", "adm1_code": 41761, "population": 18825, "loss": 1.5055303708, "wind_cat": {"0": 18825}, "adm2": [{"adm2_name": "Tsiroanomandidy", "adm2_code": 19203, "population": 18825, "loss": 1.5055303708, "wind_cat": {"0": 18825}}]}, {"adm1_name": "Haute Matsiatra", "adm1_code": 41763, "population": 1143007, "loss": 276505.0490964448, "wind_cat": {"0": 367524, "1": 775483}, "adm2": [{"adm2_name": "Ambalavao", "adm2_code": 19213, "population": 188394, "loss": 14402.1000108847, "wind_cat": {"0": 137115, "1": 51279}}, {"adm2_name": "Ambohimahasoa", "adm2_code": 19215, "population": 175554, "loss": 108294.3948117815, "wind_cat": {"0": 13426, "1": 162128}}, {"adm2_name": "Fianarantsoa I", "adm2_code": 19220, "population": 35920, "loss": 3215.5001636871, "wind_cat": {"0": 2177, "1": 33743}}, {"adm2_name": "Fianarantsoa II", "adm2_code": 19221, "population": 632513, "loss": 96201.7460560758, "wind_cat": {"0": 200202, "1": 432311}}, {"adm2_name": "Ikalamavony", "adm2_code": 19225, "population": 110626, "loss": 54391.3080540156, "wind_cat": {"0": 14604, "1": 96022}}]}, {"adm1_name": "Ihorombe", "adm1_code": 41764, "population": 308563, "loss": 5390.5694695635, "wind_cat": {"0": 267939, "1": 40624}, "adm2": [{"adm2_name": "Iakora", "adm2_code": 19222, "population": 242, "loss": 0.0012416733, "wind_cat": {"0": 242}}, {"adm2_name": "Ihosy", "adm2_code": 19224, "population": 284376, "loss": 5355.1836539185, "wind_cat": {"0": 243795, "1": 40581}}, {"adm2_name": "Ivohibe", "adm2_code": 19227, "population": 23945, "loss": 35.3845739718, "wind_cat": {"0": 23902, "1": 43}}]}, {"adm1_name": "Itasy", "adm1_code": 41765, "population": 81512, "loss": 0.5410485653, "wind_cat": {"0": 81512}, "adm2": [{"adm2_name": "Arivonimamo", "adm2_code": 19196, "population": 48639, "loss": 0.4551779282, "wind_cat": {"0": 48639}}, {"adm2_name": "Miarinarivo", "adm2_code": 19201, "population": 1368, "loss": 0.0001840077, "wind_cat": {"0": 1368}}, {"adm2_name": "Soavinandriana", "adm2_code": 19202, "population": 31505, "loss": 0.0856866294, "wind_cat": {"0": 31505}}]}, {"adm1_name": "Melaky", "adm1_code": 41766, "population": 394, "loss": 0.0014875015, "wind_cat": {"0": 394}, "adm2": [{"adm2_name": "Antsalova", "adm2_code": 19239, "population": 394, "loss": 0.0014875015, "wind_cat": {"0": 394}}]}, {"adm1_name": "Menabe", "adm1_code": 41767, "population": 608702, "loss": 76842.7559305661, "wind_cat": {"0": 333993, "1": 274709}, "adm2": [{"adm2_name": "Belon'i Tsiribihina", "adm2_code": 19281, "population": 133135, "loss": 382.8041922737, "wind_cat": {"0": 126417, "1": 6718}}, {"adm2_name": "Mahabo", "adm2_code": 19286, "population": 140351, "loss": 53027.4465899187, "wind_cat": {"0": 22188, "1": 118163}}, {"adm2_name": "Manja", "adm2_code": 19287, "population": 62485, "loss": 7666.977598054, "wind_cat": {"0": 33605, "1": 28880}}, {"adm2_name": "Miandrivazo", "adm2_code": 19288, "population": 98387, "loss": 467.925177978, "wind_cat": {"0": 95151, "1": 3236}}, {"adm2_name": "Morondava", "adm2_code": 19290, "population": 174344, "loss": 15297.6023723417, "wind_cat": {"0": 56632, "1": 117712}}]}, {"adm1_name": "Vakinakaratra", "adm1_code": 41770, "population": 1167613, "loss": 9741.6589924311, "wind_cat": {"0": 1134531, "1": 33082}, "adm2": [{"adm2_name": "Ambatolampy", "adm2_code": 19185, "population": 137682, "loss": 29.6617669305, "wind_cat": {"0": 137682}}, {"adm2_name": "Antanifotsy", "adm2_code": 19193, "population": 179403, "loss": 1393.5641906833, "wind_cat": {"0": 179273, "1": 130}}, {"adm2_name": "Antsirabe I", "adm2_code": 19194, "population": 28020, "loss": 23.2345481017, "wind_cat": {"0": 28020}}, {"adm2_name": "Antsirabe II", "adm2_code": 19195, "population": 236803, "loss": 4680.5967019774, "wind_cat": {"0": 229182, "1": 7621}}, {"adm2_name": "Betafo", "adm2_code": 19197, "population": 409162, "loss": 3439.7764656514, "wind_cat": {"0": 383831, "1": 25331}}, {"adm2_name": "Faratsiho", "adm2_code": 19198, "population": 176543, "loss": 174.8253190869, "wind_cat": {"0": 176543}}]}, {"adm1_name": "Vatovavy Fitovinany", "adm1_code": 41771, "population": 1503075, "loss": 6109.9272974785, "wind_cat": {"0": 1487289, "1": 15786}, "adm2": [{"adm2_name": "Ifanadiana", "adm2_code": 19223, "population": 147502, "loss": 1946.7133788449, "wind_cat": {"0": 138784, "1": 8718}}, {"adm2_name": "Ikongo", "adm2_code": 19226, "population": 248178, "loss": 127.6084238682, "wind_cat": {"0": 245922, "1": 2256}}, {"adm2_name": "Manakara", "adm2_code": 19228, "population": 402302, "loss": 134.601046119, "wind_cat": {"0": 402302}}, {"adm2_name": "Mananjary", "adm2_code": 19230, "population": 374007, "loss": 3581.5674081761, "wind_cat": {"0": 369195, "1": 4812}}, {"adm2_name": "Nosy-Varika", "adm2_code": 19232, "population": 248590, "loss": 316.7520275065, "wind_cat": {"0": 248590}}, {"adm2_name": "Vohipeno", "adm2_code": 19234, "population": 82496, "loss": 2.6850129638, "wind_cat": {"0": 82496}}]}]}], "utc_timestamp": "2024-01-02 03:41:55 UTC"}