{"records": [{"adm0_name": "Mauritius", "adm0_code": 160, "population": 1227900, "loss": 6237463.08131752, "wind_cat": {"0": 22130, "1": 1197244, "2": 8526}, "adm1": [{"adm1_name": "Administrative unit not available", "adm1_code": 2017, "population": 307, "loss": 97.6059759803, "wind_cat": {"1": 307}, "adm2": [{"adm2_name": "Administrative unit not available", "adm2_code": 19535, "population": 307, "loss": 97.6059759803, "wind_cat": {"1": 307}}]}, {"adm1_name": "Black River", "adm1_code": 2018, "population": 72490, "loss": 1583478.2502700274, "wind_cat": {"1": 67670, "2": 4820}, "adm2": [{"adm2_name": "Administrative unit not available", "adm2_code": 19536, "population": 72490, "loss": 1583478.2502700274, "wind_cat": {"1": 67670, "2": 4820}}]}, {"adm1_name": "Flacq", "adm1_code": 2019, "population": 148203, "loss": 143486.2460836108, "wind_cat": {"0": 5640, "1": 142563}, "adm2": [{"adm2_name": "Administrative unit not available", "adm2_code": 19537, "population": 148203, "loss": 143486.2460836108, "wind_cat": {"0": 5640, "1": 142563}}]}, {"adm1_name": "Grand Port", "adm1_code": 2020, "population": 117962, "loss": 602788.3404064495, "wind_cat": {"1": 117962}, "adm2": [{"adm2_name": "Administrative unit not available", "adm2_code": 19538, "population": 117962, "loss": 602788.3404064495, "wind_cat": {"1": 117962}}]}, {"adm1_name": "Moka", "adm1_code": 2021, "population": 144916, "loss": 562311.6981227078, "wind_cat": {"1": 144916}, "adm2": [{"adm2_name": "Administrative unit not available", "adm2_code": 19539, "population": 144916, "loss": 562311.6981227078, "wind_cat": {"1": 144916}}]}, {"adm1_name": "Pamplemousses", "adm1_code": 2022, "population": 165109, "loss": 592232.7530042046, "wind_cat": {"1": 165109}, "adm2": [{"adm2_name": "Administrative unit not available", "adm2_code": 19540, "population": 165109, "loss": 592232.7530042046, "wind_cat": {"1": 165109}}]}, {"adm1_name": "Plaines Wilhems", "adm1_code": 2023, "population": 294342, "loss": 678887.3773798482, "wind_cat": {"1": 294228, "2": 114}, "adm2": [{"adm2_name": "Administrative unit not available", "adm2_code": 19541, "population": 294342, "loss": 678887.3773798482, "wind_cat": {"1": 294228, "2": 114}}]}, {"adm1_name": "Port Louis", "adm1_code": 2024, "population": 100326, "loss": 76210.0973704946, "wind_cat": {"1": 100326}, "adm2": [{"adm2_name": "Administrative unit not available", "adm2_code": 19542, "population": 100326, "loss": 76210.0973704946, "wind_cat": {"1": 100326}}]}, {"adm1_name": "Riviere Du Rempart", "adm1_code": 2025, "population": 123738, "loss": 92536.4741628619, "wind_cat": {"0": 16490, "1": 107248}, "adm2": [{"adm2_name": "Administrative unit not available", "adm2_code": 19543, "population": 123738, "loss": 92536.4741628619, "wind_cat": {"0": 16490, "1": 107248}}]}, {"adm1_name": "Savanne", "adm1_code": 2026, "population": 60507, "loss": 1905434.2385413344, "wind_cat": {"1": 56915, "2": 3592}, "adm2": [{"adm2_name": "Administrative unit not available", "adm2_code": 19544, "population": 60507, "loss": 1905434.2385413344, "wind_cat": {"1": 56915, "2": 3592}}]}]}, {"adm0_name": "R\u00e9union", "adm0_code": 206, "population": 704518, "loss": 4213133047.854937, "wind_cat": {"3": 394089, "4": 310429}, "adm1": [{"adm1_name": "Arrondissement_du_vent", "adm1_code": 2590, "population": 256754, "loss": 1472343968.873482, "wind_cat": {"3": 31156, "4": 225598}, "adm2": [{"adm2_name": "Administrative unit not available", "adm2_code": 25273, "population": 256754, "loss": 1472343968.873482, "wind_cat": {"3": 31156, "4": 225598}}]}, {"adm1_name": "Arrondissement_souse_le_vent", "adm1_code": 2591, "population": 447764, "loss": 2740789078.9814553, "wind_cat": {"3": 362933, "4": 84831}, "adm2": [{"adm2_name": "Administrative unit not available", "adm2_code": 25274, "population": 447764, "loss": 2740789078.9814553, "wind_cat": {"3": 362933, "4": 84831}}]}]}], "utc_timestamp": "2024-01-13 18:38:54 UTC"}