{"records": [{"adm0_name": "Mauritius", "adm0_code": 160, "population": 1227900, "loss": 20390054.069271322, "wind_cat": {"1": 1119360, "2": 108540}, "adm1": [{"adm1_name": "Administrative unit not available", "adm1_code": 2017, "population": 307, "loss": 1675.8514912321, "wind_cat": {"1": 307}, "adm2": [{"adm2_name": "Administrative unit not available", "adm2_code": 19535, "population": 307, "loss": 1675.8514912321, "wind_cat": {"1": 307}}]}, {"adm1_name": "Black River", "adm1_code": 2018, "population": 72490, "loss": 1439143.3315911938, "wind_cat": {"1": 72226, "2": 264}, "adm2": [{"adm2_name": "Administrative unit not available", "adm2_code": 19536, "population": 72490, "loss": 1439143.3315911938, "wind_cat": {"1": 72226, "2": 264}}]}, {"adm1_name": "Flacq", "adm1_code": 2019, "population": 148203, "loss": 4289888.129728491, "wind_cat": {"1": 119284, "2": 28919}, "adm2": [{"adm2_name": "Administrative unit not available", "adm2_code": 19537, "population": 148203, "loss": 4289888.129728491, "wind_cat": {"1": 119284, "2": 28919}}]}, {"adm1_name": "Grand Port", "adm1_code": 2020, "population": 117962, "loss": 5409550.374228051, "wind_cat": {"1": 62796, "2": 55166}, "adm2": [{"adm2_name": "Administrative unit not available", "adm2_code": 19538, "population": 117962, "loss": 5409550.374228051, "wind_cat": {"1": 62796, "2": 55166}}]}, {"adm1_name": "Moka", "adm1_code": 2021, "population": 144916, "loss": 1270375.910393864, "wind_cat": {"1": 144916}, "adm2": [{"adm2_name": "Administrative unit not available", "adm2_code": 19539, "population": 144916, "loss": 1270375.910393864, "wind_cat": {"1": 144916}}]}, {"adm1_name": "Pamplemousses", "adm1_code": 2022, "population": 165109, "loss": 2290743.318135103, "wind_cat": {"1": 165109}, "adm2": [{"adm2_name": "Administrative unit not available", "adm2_code": 19540, "population": 165109, "loss": 2290743.318135103, "wind_cat": {"1": 165109}}]}, {"adm1_name": "Plaines Wilhems", "adm1_code": 2023, "population": 294342, "loss": 870461.5656071292, "wind_cat": {"1": 294267, "2": 75}, "adm2": [{"adm2_name": "Administrative unit not available", "adm2_code": 19541, "population": 294342, "loss": 870461.5656071292, "wind_cat": {"1": 294267, "2": 75}}]}, {"adm1_name": "Port Louis", "adm1_code": 2024, "population": 100326, "loss": 189693.1812920309, "wind_cat": {"1": 100326}, "adm2": [{"adm2_name": "Administrative unit not available", "adm2_code": 19542, "population": 100326, "loss": 189693.1812920309, "wind_cat": {"1": 100326}}]}, {"adm1_name": "Riviere Du Rempart", "adm1_code": 2025, "population": 123738, "loss": 1417478.0233286724, "wind_cat": {"1": 123738, "2": 0}, "adm2": [{"adm2_name": "Administrative unit not available", "adm2_code": 19543, "population": 123738, "loss": 1417478.0233286724, "wind_cat": {"1": 123738, "2": 0}}]}, {"adm1_name": "Savanne", "adm1_code": 2026, "population": 60507, "loss": 3211044.3834755532, "wind_cat": {"1": 36391, "2": 24116}, "adm2": [{"adm2_name": "Administrative unit not available", "adm2_code": 19544, "population": 60507, "loss": 3211044.3834755532, "wind_cat": {"1": 36391, "2": 24116}}]}]}, {"adm0_name": "R\u00e9union", "adm0_code": 206, "population": 651437, "loss": 1439456.1204495174, "wind_cat": {"0": 276744, "1": 374693}, "adm1": [{"adm1_name": "Arrondissement_du_vent", "adm1_code": 2590, "population": 203673, "loss": 12100.1957620702, "wind_cat": {"0": 181360, "1": 22313}, "adm2": [{"adm2_name": "Administrative unit not available", "adm2_code": 25273, "population": 203673, "loss": 12100.1957620702, "wind_cat": {"0": 181360, "1": 22313}}]}, {"adm1_name": "Arrondissement_souse_le_vent", "adm1_code": 2591, "population": 447764, "loss": 1427355.924687447, "wind_cat": {"0": 95384, "1": 352380}, "adm2": [{"adm2_name": "Administrative unit not available", "adm2_code": 25274, "population": 447764, "loss": 1427355.924687447, "wind_cat": {"0": 95384, "1": 352380}}]}]}], "utc_timestamp": "2024-02-20 00:54:00 UTC"}